{
  "type": "object",
  "title": "Dynaform",
  "properties": {
    "country": {
      "type": "object",
      "description": "",
      "i18n": "country"
    },
    "subdivision": {
      "type": "object",
      "description": "",
      "i18n": "subdivision"
    },
    "location": {
      "type": "object",
      "description": "",
      "i18n": "location"
    },
    "countrys": {
      "type": "object",
      "description": "",
      "i18n": "countrys"
    },
    "subdivisions": {
      "type": "object",
      "description": "",
      "i18n": "subdivisions"
    },
    "locations": {
      "type": "object",
      "description": "",
      "i18n": "locations"
    }
  }
}
